{"pageProps":{"slug":"leander-vs-cedar-park-real-estate-market-comparison-2026","title":"leander vs cedar park real estate market comparison 2026","date":"2026-03-04T12:14:44.983Z","contentHtml":"<h1>Leander vs Cedar Park Real Estate Market Comparison 2026: Your Ultimate Local Guide</h1>\n<p>As a trusted Texas real estate agent specializing in Leander, Cedar Park, and the greater Austin area, I understand how critical it is for homebuyers, sellers, and investors to make informed decisions in today’s dynamic market. If you’re asking, <strong>“Leander vs Cedar Park real estate market comparison 2026,”</strong> you’ve landed in the right place. This comprehensive guide dives deep into the unique market characteristics, lifestyle differences, and investment potential of these two thriving Texas cities to help you decide which community fits your real estate goals best.</p>\n<hr>\n<h2>Understanding the Leander vs Cedar Park Real Estate Market in 2026</h2>\n<p>Both Leander and Cedar Park have experienced significant growth over the past decade, fueled by Austin’s booming economy and expanding tech sectors. However, each city offers its own distinct flavor of living, housing options, and community amenities.</p>\n<h3>Why 2026 is a Critical Year for Buyers and Sellers</h3>\n<p>The Austin metro area continues evolving as remote work trends, infrastructure projects, and demographic shifts reshape demand. In 2026, buyers and sellers must evaluate not just price points but also long-term quality of life, school zoning, and neighborhood growth patterns. This Leander vs Cedar Park real estate market comparison 2026 aims to clarify these nuances.</p>\n<hr>\n<h2>Neighborhoods &#x26; Community Vibes: Leander vs Cedar Park</h2>\n<h3>Leander: Suburban Growth with Hill Country Charm</h3>\n<ul>\n<li><strong>Neighborhood Highlights:</strong> Crystal Falls, Rough Hollow, and Teravista are standout communities featuring large lots, newer builds, and scenic hill country views.</li>\n<li><strong>Community Feel:</strong> Leander boasts a more relaxed, suburban atmosphere with ample parks like Lakewood Park and access to the beautiful Balcones Canyonlands Preserve.</li>\n<li><strong>Local Events:</strong> The annual Leander Bluegrass Festival and the Leander Farmer’s Market foster a tight-knit, family-friendly community spirit.</li>\n</ul>\n<h3>Cedar Park: Urban-Suburban Blend with Convenient Access</h3>\n<ul>\n<li><strong>Neighborhood Highlights:</strong> Whitestone, Brushy Creek, and North Lakeline offer diverse housing options from cozy townhomes to upscale single-family homes.</li>\n<li><strong>Community Feel:</strong> Cedar Park provides a vibrant mix of retail, dining, and entertainment, anchored by the H-E-B Center and numerous local businesses along 183A Toll Road.</li>\n<li><strong>Local Events:</strong> Cedar Park hosts the popular Cedar Park Music Festival and a thriving farmers market scene that attracts locals year-round.</li>\n</ul>\n<hr>\n<h2>Home Prices and Market Trends</h2>\n<h3>Current Market Snapshot</h3>\n<ul>\n<li><strong>Leander:</strong> Typically offers more affordable housing options with larger lot sizes. New construction dominates, attracting buyers seeking modern amenities and space for growing families.</li>\n<li><strong>Cedar Park:</strong> Slightly higher median home prices reflect its proximity to Austin and established infrastructure. The market includes a mix of older homes and newer developments.</li>\n</ul>\n<h3>What to Expect in 2026</h3>\n<ul>\n<li>Both cities will likely continue appreciating in value, driven by sustained demand in the Austin metro.</li>\n<li>Leander may appeal more to first-time buyers and those looking for room to grow.</li>\n<li>Cedar Park’s market will remain competitive among professionals seeking shorter commutes and urban conveniences.</li>\n</ul>\n<hr>\n<h2>Schools and Education: What Local Families Should Know</h2>\n<p>While I avoid rating schools, it’s important to recognize the role of school districts in your decision:</p>\n<ul>\n<li><strong>Leander ISD</strong> serves the Leander area, with several new campuses opening to accommodate rapid population growth.</li>\n<li><strong>Cedar Park</strong> is primarily served by the Leander ISD and Round Rock ISD, depending on the neighborhood.</li>\n<li>Proximity to schools like Danielson Elementary in Leander or Lakeline Elementary in Cedar Park can impact home values and resale appeal.</li>\n</ul>\n<hr>\n<h2>Commute and Transportation Insights</h2>\n<h3>Leander</h3>\n<ul>\n<li>Located about 30 miles northwest of downtown Austin.</li>\n<li>Access via US-183 and TX-183A Toll Road.</li>\n<li>Capital Metro’s commuter rail (the MetroRail Red Line) connects Leander directly to Austin, offering a stress-free alternative to driving.</li>\n</ul>\n<h3>Cedar Park</h3>\n<ul>\n<li>Approximately 20 miles northwest of downtown Austin.</li>\n<li>Well-connected by toll roads and highways including 183A and SH-45.</li>\n<li>Shorter average commute times compared to Leander, making it attractive for daily Austin commuters.</li>\n</ul>\n<hr>\n<h2>Lifestyle and Amenities: What Sets Each City Apart?</h2>\n<h3>Leander</h3>\n<ul>\n<li>Known for outdoor recreation opportunities: hiking trails, nearby lakes like Lake Georgetown, and community parks.</li>\n<li>Family-oriented amenities with new community centers and sports complexes.</li>\n<li>Growing retail and dining options but still less dense than Cedar Park.</li>\n</ul>\n<h3>Cedar Park</h3>\n<ul>\n<li>Offers a more developed commercial scene with shopping centers, craft breweries, and restaurants.</li>\n<li>Home to the H-E-B Center, hosting concerts, sports, and family events.</li>\n<li>Strong focus on community events, including farmers markets and holiday festivities.</li>\n</ul>\n<hr>\n<h2>Investment Potential: Which Market Offers More?</h2>\n<p>Real estate investors eyeing Leander vs Cedar Park in 2026 should weigh:</p>\n<ul>\n<li><strong>Leander:</strong> Potential for higher returns through new developments and increasing demand for affordable housing on Austin’s outskirts.</li>\n<li><strong>Cedar Park:</strong> Stability and steady appreciation, with strong rental demand from professionals working in Austin’s tech corridor.</li>\n</ul>\n<hr>\n<h2>Joe’s Insider Tips for Buyers and Sellers in Leander and Cedar Park</h2>\n<ul>\n<li><strong>For Buyers:</strong> Consider future infrastructure projects like new schools, road expansions, and commercial developments that might impact home values.</li>\n<li><strong>For Sellers:</strong> Timing your sale around local events and school enrollment periods can maximize visibility.</li>\n<li><strong>Neighborhood Nuances:</strong> Some Leander neighborhoods are more family-centric, while certain Cedar Park areas attract young professionals—know your target market.</li>\n<li><strong>Work with a Local Expert:</strong> I have firsthand knowledge of every corner of these cities and can help you navigate negotiations, inspections, and closing smoothly.</li>\n</ul>\n<hr>\n<h2>FAQs: Leander vs Cedar Park Real Estate Market Comparison 2026</h2>\n<p><strong>Q1: Which city is more affordable for first-time homebuyers?</strong><br>\nA1: Leander generally offers more affordable options with larger lots and newer homes, making it attractive for first-time buyers.</p>\n<p><strong>Q2: How do the commute times compare between Leander and Cedar Park?</strong><br>\nA2: Cedar Park has shorter average commute times to downtown Austin, while Leander benefits from the MetroRail Red Line for public transit options.</p>\n<p><strong>Q3: Are there good new construction opportunities in both cities?</strong><br>\nA3: Yes, both Leander and Cedar Park have active new home developments, though Leander’s are often on larger lots with more space.</p>\n<p><strong>Q4: What types of amenities can I expect in each city?</strong><br>\nA4: Leander offers more outdoor and family-focused amenities, while Cedar Park features a more urbanized retail and entertainment scene.</p>\n<p><strong>Q5: How do school districts impact home buying decisions here?</strong><br>\nA5: Both cities are served primarily by Leander ISD, with some Cedar Park areas in Round Rock ISD; proximity to schools can affect home values and resale.</p>\n<hr>\n<h2>Final Thoughts: Making the Right Choice for Your 2026 Home</h2>\n<p>Choosing between Leander and Cedar Park comes down to your lifestyle preferences, budget, and long-term goals. Whether you value spacious homes surrounded by nature or prefer a bustling community with easy access to Austin’s urban core, both cities have much to offer.</p>\n<p>If you want personalized insights tailored to your unique needs in the Leander vs Cedar Park real estate market comparison 2026, don’t hesitate to reach out. I’m Joe F. Sanches, your local expert ready to guide you every step of the way.</p>\n<hr>\n<h3>Ready to explore homes or sell your property in Leander, Cedar Park, or Austin?</h3>\n<p>Call or text me today at (512) XXX-XXXX or visit <a href=\"https://joefsanches.com\">joefsanches.com</a> to fill out the contact form and get started!</p>\n<hr>\n<h3>Suggested Internal Links for Further Reading:</h3>\n<ul>\n<li>Learn more about <strong>Leander’s Best Neighborhoods for Families</strong> in our guide to <a href=\"#\">Top Family-Friendly Communities in Leander</a></li>\n<li>Discover the <strong>Cedar Park lifestyle and amenities</strong> in our post on <a href=\"#\">Living in Cedar Park: What You Need to Know</a></li>\n<li>Explore the <strong>Austin metro real estate trends</strong> with our analysis in <a href=\"#\">Austin Area Housing Market Update 2026</a></li>\n</ul>\n<hr>\n<h3>Meta Description Suggestion:</h3>\n<p>Leander vs Cedar Park real estate market comparison 2026: Discover local insights, neighborhood highlights, and expert advice to find your perfect Texas home.</p>\n","description":"\n Leander vs Cedar Park Real Estate Market Comparison 2026: Your Ultimate Local Guide\n\nAs a trusted Texas real estate agent specializing in Leander, Cedar Park,"},"__N_SSG":true}